{
  "Routes": [
    {
      "DownstreamPathTemplate": "/Authentication/Login",
      "DownstreamScheme": "http",
      "DownstreamHostAndPorts": [
        {
          "Host": "localhost",
          "Port": "5200"
        }
      ],
      "UpstreamPathTemplate": "/login",
      "UpstreamHttpMethod": [ "Get" ]
    },
    {
      "DownstreamPathTemplate": "/Account/GetUsers",
      "DownstreamScheme": "http",
      "DownstreamHostAndPorts": [
        {
          "Host": "localhost",
          "Port": "5100"
        }
      ],
      "UpstreamPathTemplate": "/userlist",
      "UpstreamHttpMethod": [ "Get" ]
    },
    {
      "DownstreamPathTemplate": "/Account/Create",
      "DownstreamScheme": "http",
      "DownstreamHostAndPorts": [
        {
          "Host": "localhost",
          "Port": "5100"
        }
      ],
      "UpstreamPathTemplate": "/user/create",
      "UpstreamHttpMethod": [ "Post" ]
    },
    {
      "DownstreamPathTemplate": "/Account/Update",
      "DownstreamScheme": "http",
      "DownstreamHostAndPorts": [
        {
          "Host": "localhost",
          "Port": "5100"
        }
      ],
      "UpstreamPathTemplate": "/user/update",
      "UpstreamHttpMethod": [ "Post" ]
    },
    {
      "DownstreamPathTemplate": "/Account/Delete",
      "DownstreamScheme": "http",
      "DownstreamHostAndPorts": [
        {
          "Host": "localhost",
          "Port": "5100"
        }
      ],
      "UpstreamPathTemplate": "/user/delete",
      "UpstreamHttpMethod": [ "Delete" ]
    },
    {
      "DownstreamPathTemplate": "/Products/All",
      "DownstreamScheme": "http",
      "DownstreamHostAndPorts": [
        {
          "Host": "localhost",
          "Port": "5300"
        }
      ],
      "UpstreamPathTemplate": "/products",
      "UpstreamHttpMethod": [ "Get" ]
    },
    {
      "DownstreamPathTemplate": "/Products/ForBusket/{id}",
      "DownstreamScheme": "http",
      "DownstreamHostAndPorts": [
        {
          "Host": "localhost",
          "Port": "5300"
        }
      ],
      "UpstreamPathTemplate": "/product/forBusket/{id}",
      "UpstreamHttpMethod": [ "Get" ]
    },
    {
      "DownstreamPathTemplate": "/Products/Create",
      "DownstreamScheme": "http",
      "DownstreamHostAndPorts": [
        {
          "Host": "localhost",
          "Port": "5300"
        }
      ],
      "UpstreamPathTemplate": "/product/create",
      "UpstreamHttpMethod": [ "Post" ]
    },
    {
      "DownstreamPathTemplate": "/Products/Update",
      "DownstreamScheme": "http",
      "DownstreamHostAndPorts": [
        {
          "Host": "localhost",
          "Port": "5300"
        }
      ],
      "UpstreamPathTemplate": "/product/update",
      "UpstreamHttpMethod": [ "Post" ]
    },
    {
      "DownstreamPathTemplate": "/Products/Delete/{id}",
      "DownstreamScheme": "http",
      "DownstreamHostAndPorts": [
        {
          "Host": "localhost",
          "Port": "5300"
        }
      ],
      "UpstreamPathTemplate": "/product/delete/{id}",
      "UpstreamHttpMethod": [ "Delete" ]
    },
    {
      "DownstreamPathTemplate": "/Products/GetProduct/{id}",
      "DownstreamScheme": "http",
      "DownstreamHostAndPorts": [
        {
          "Host": "localhost",
          "Port": "5300"
        }
      ],
      "UpstreamPathTemplate": "/product/get/{id}",
      "UpstreamHttpMethod": [ "Get" ]
    },
    {
      "DownstreamPathTemplate": "/Categories/All",
      "DownstreamScheme": "http",
      "DownstreamHostAndPorts": [
        {
          "Host": "localhost",
          "Port": "5300"
        }
      ],
      "UpstreamPathTemplate": "/categories",
      "UpstreamHttpMethod": [ "Get" ]
    },
    {
      "DownstreamPathTemplate": "/Categories/Create",
      "DownstreamScheme": "http",
      "DownstreamHostAndPorts": [
        {
          "Host": "localhost",
          "Port": "5300"
        }
      ],
      "UpstreamPathTemplate": "/category/create",
      "UpstreamHttpMethod": [ "Post" ]
    },
    {
      "DownstreamPathTemplate": "/Categories/Remove/{id}",
      "DownstreamScheme": "http",
      "DownstreamHostAndPorts": [
        {
          "Host": "localhost",
          "Port": "5300"
        }
      ],
      "UpstreamPathTemplate": "/category/remove/{id}",
      "UpstreamHttpMethod": [ "Delete" ]
    },
    {
      "DownstreamPathTemplate": "/busketlist",
      "DownstreamScheme": "http",
      "DownstreamHostAndPorts": [
        {
          "Host": "localhost",
          "Port": "5700"
        }
      ],
      "UpstreamPathTemplate": "/SmartShop/Busket",
      "UpstreamHttpMethod": [ "Get", "Post" ]
    },
    {
      "DownstreamPathTemplate": "/Busket/Add/{id}",
      "DownstreamScheme": "http",
      "DownstreamHostAndPorts": [
        {
          "Host": "localhost",
          "Port": "5400"
        }
      ],
      "UpstreamPathTemplate": "/Busket/Add/{id}",
      "UpstreamHttpMethod": [ "Get" ]
    },
    {
      "DownstreamPathTemplate": "/orderlist",
      "DownstreamScheme": "http",
      "DownstreamHostAndPorts": [
        {
          "Host": "localhost",
          "Port": "5700"
        }
      ],
      "UpstreamPathTemplate": "/SmartShop/Orders",
      "UpstreamHttpMethod": [ "Get", "Post" ]
    },
    {
      "DownstreamPathTemplate": "/Order/Make",
      "DownstreamScheme": "http",
      "DownstreamHostAndPorts": [
        {
          "Host": "localhost",
          "Port": "5500"
        }
      ],
      "UpstreamPathTemplate": "/Order/Make",
      "UpstreamHttpMethod": [ "Get" ]
    },
    {
      "DownstreamPathTemplate": "/Order/Remove/{id}",
      "DownstreamScheme": "http",
      "DownstreamHostAndPorts": [
        {
          "Host": "localhost",
          "Port": "5500"
        }
      ],
      "UpstreamPathTemplate": "/Order/Remove/{id}",
      "UpstreamHttpMethod": [ "Delete" ]
    },
    {
      "DownstreamPathTemplate": "/Order/Ship/{id}",
      "DownstreamScheme": "http",
      "DownstreamHostAndPorts": [
        {
          "Host": "localhost",
          "Port": "5500"
        }
      ],
      "UpstreamPathTemplate": "/Order/Ship/{id}",
      "UpstreamHttpMethod": [ "Post" ]
    },
    {
      "DownstreamPathTemplate": "/AccountPages/Users",
      "DownstreamScheme": "http",
      "DownstreamHostAndPorts": [
        {
          "Host": "localhost",
          "Port": "5700"
        }
      ],
      "UpstreamPathTemplate": "/SmartShop/Users",
      "UpstreamHttpMethod": [ "Get" ]
    },
    {
      "DownstreamPathTemplate": "/getuser",
      "DownstreamScheme": "http",
      "DownstreamHostAndPorts": [
        {
          "Host": "localhost",
          "Port": "5700"
        }
      ],
      "UpstreamPathTemplate": "/SmartShop/CurrentUser",
      "UpstreamHttpMethod": [ "Get", "Post" ]
    },
    {
      "DownstreamPathTemplate": "/createuser",
      "DownstreamScheme": "http",
      "DownstreamHostAndPorts": [
        {
          "Host": "localhost",
          "Port": "5700"
        }
      ],
      "UpstreamPathTemplate": "/SmartShop/UserAccount/Create",
      "UpstreamHttpMethod": [ "Get", "Post" ]
    },
    {
      "DownstreamPathTemplate": "/updateuser/{id}",
      "DownstreamScheme": "http",
      "DownstreamHostAndPorts": [
        {
          "Host": "localhost",
          "Port": "5700"
        }
      ],
      "UpstreamPathTemplate": "/SmartShop/UserAccount/Update/{id}",
      "UpstreamHttpMethod": [ "Get", "Post" ]
    },
    {
      "DownstreamPathTemplate": "/loginpage",
      "DownstreamScheme": "http",
      "DownstreamHostAndPorts": [
        {
          "Host": "localhost",
          "Port": "5700"
        }
      ],
      "UpstreamPathTemplate": "/SmartShop/Login",
      "UpstreamHttpMethod": [ "Get", "Post" ]
    },
    {
      "DownstreamPathTemplate": "/productlist",
      "DownstreamScheme": "http",
      "DownstreamHostAndPorts": [
        {
          "Host": "localhost",
          "Port": "5700"
        }
      ],
      "UpstreamPathTemplate": "/SmartShop/Products",
      "UpstreamHttpMethod": [ "Get", "Post" ]
    },
    {
      "DownstreamPathTemplate": "/createproduct",
      "DownstreamScheme": "http",
      "DownstreamHostAndPorts": [
        {
          "Host": "localhost",
          "Port": "5700"
        }
      ],
      "UpstreamPathTemplate": "/SmartShop/Products/Create",
      "UpstreamHttpMethod": [ "Get", "Post" ]
    },
    {
      "DownstreamPathTemplate": "/updateproduct/{id}",
      "DownstreamScheme": "http",
      "DownstreamHostAndPorts": [
        {
          "Host": "localhost",
          "Port": "5700"
        }
      ],
      "UpstreamPathTemplate": "/SmartShop/Products/Update/{id}",
      "UpstreamHttpMethod": [ "Get", "Post" ]
    },

    {
      "DownstreamPathTemplate": "/startpage",
      "DownstreamScheme": "http",
      "DownstreamHostAndPorts": [
        {
          "Host": "localhost",
          "Port": "5700"
        }
      ],
      "UpstreamPathTemplate": "/SmartShop/Start",
      "UpstreamHttpMethod": [ "Get", "Post" ]
    }

  ],
  "GlobalConfiguration": {
    "BaseUrl": "http://localhost:5000"
  
  }
}
